shrug_lang/__init__.py
shrug_lang/errors.py
shrug_lang/interpreter.py
shrug_lang/operators.py
shrug_lang/parser_state.py
shrug_lang/shrug_token.py
shrug_lang/token_parser.py
shrug_lang/tokenizer.py
shrug_lang-0.1.0.dist-info/METADATA
shrug_lang-0.1.0.dist-info/RECORD
shrug_lang-0.1.0.dist-info/WHEEL
shrug_lang-0.1.0.dist-info/entry_points.txt
shrug_lang-0.1.0.dist-info/top_level.txt
tests/__init__.py
tests/test_base_ops.py
tests/test_comp_ops.py
tests/test_cond_parsing.py
tests/test_math_ops.py
tests/test_token.py
tests/test_token_parser.py
tests/test_tokenizer.py
tests/utils.py
