Metadata-Version: 2.1
Name: shrug-lang
Version: 0.1.0
Summary: Interpreter for the Shrug Programming Language
Home-page: https://github.com/Ben-Wu/ShrugProgrammingLanguage
Maintainer: Ben Wu
Maintainer-email: bwub124@gmail.com
License: UNKNOWN
Platform: UNKNOWN
Classifier: License :: OSI Approved :: MIT License
Classifier: Programming Language :: Python :: 3.6
Classifier: Programming Language :: Python :: 3.7
Classifier: Programming Language :: Python :: 3 :: Only
Classifier: Development Status :: 3 - Alpha
Requires-Dist: dataclasses
